{
  "as_of": "2026-07-15",
  "generated": "2026-07-16 00:13 UTC",
  "risk": {
    "score": 32,
    "regime": "NEUTRAL",
    "components": {
      "Rate Vol (MOVE)": {
        "pct": 17.6039119804401,
        "weight": 0.25
      },
      "HY Credit": {
        "pct": 18.663594470046082,
        "weight": 0.3
      },
      "IG Credit (BBB)": {
        "pct": 21.658986175115206,
        "weight": 0.2
      },
      "Yield Curve (2-10)": {
        "pct": 71.84466019417476,
        "weight": 0.25
      }
    }
  },
  "panels": {
    "MOVE": {
      "metrics": {
        "last": 68.47799682617188,
        "d1": 69.55000305175781,
        "w1": 72.41000366210938,
        "m1": 69.37999725341797,
        "last_dt": "2026-07-15",
        "dod": [
          -107.20062255859375,
          -1.5413460511111254
        ],
        "wow": [
          -393.20068359375,
          -5.430198366355055
        ],
        "mom": [
          -90.20004272460938,
          -1.3000871475267406
        ]
      },
      "trend": {
        "trend": "Falling",
        "change": false,
        "score": 0,
        "strength": "-",
        "z": -0.6499463100368194
      },
      "kind": "vol",
      "name": "MOVE"
    },
    "HY_OAS": {
      "metrics": {
        "last": 2.72,
        "d1": 2.69,
        "w1": 2.67,
        "m1": 2.71,
        "last_dt": "2026-07-14",
        "dod": [
          3.000000000000025,
          1.115241635687747
        ],
        "wow": [
          5.000000000000027,
          1.8726591760299671
        ],
        "mom": [
          1.000000000000023,
          0.3690036900369176
        ]
      },
      "trend": {
        "trend": "Rising",
        "change": true,
        "score": 35,
        "strength": "Weak",
        "z": -0.6159515609683044
      },
      "kind": "credit",
      "name": "HY OAS"
    },
    "BBB_OAS": {
      "metrics": {
        "last": 0.97,
        "d1": 0.96,
        "w1": 0.94,
        "m1": 0.93,
        "last_dt": "2026-07-14",
        "dod": [
          1.0000000000000009,
          1.041666666666674
        ],
        "wow": [
          3.0000000000000027,
          3.1914893617021267
        ],
        "mom": [
          3.9999999999999925,
          4.3010752688172005
        ]
      },
      "trend": {
        "trend": "Rising",
        "change": true,
        "score": 40,
        "strength": "Moderate",
        "z": 0.6124828391016894
      },
      "kind": "credit",
      "name": "BBB OAS"
    },
    "CURVE": {
      "metrics": {
        "last": 0.40000000000000036,
        "d1": 0.3600000000000003,
        "w1": 0.35999999999999943,
        "m1": 0.39000000000000057,
        "last_dt": "2026-07-14",
        "dod": [
          4.0000000000000036,
          11.111111111111116
        ],
        "wow": [
          4.000000000000092,
          11.111111111111382
        ],
        "mom": [
          0.9999999999999787,
          2.5641025641025106
        ]
      },
      "trend": {
        "trend": "Rising",
        "change": true,
        "score": 35,
        "strength": "Weak",
        "z": -0.3539297009460364
      },
      "kind": "curve",
      "name": "2-10 Spread",
      "regime": "Bear Steepener",
      "interp": "Long-end selling off faster",
      "spread_level": 0.40000000000000036,
      "m2": {
        "last": 4.18,
        "d1": 4.26,
        "w1": 4.19,
        "m1": 4.09,
        "last_dt": "2026-07-14",
        "dod": [
          -8.000000000000007,
          -1.8779342723004744
        ],
        "wow": [
          -1.0000000000000675,
          -0.23866348448688957
        ],
        "mom": [
          8.999999999999986,
          2.2004889975550057
        ]
      },
      "m10": {
        "last": 4.58,
        "d1": 4.62,
        "w1": 4.55,
        "m1": 4.48,
        "last_dt": "2026-07-14",
        "dod": [
          -4.0000000000000036,
          -0.8658008658008698
        ],
        "wow": [
          3.000000000000025,
          0.659340659340657
        ],
        "mom": [
          9.999999999999964,
          2.232142857142838
        ]
      }
    }
  },
  "highlights": {
    "risk_off": [],
    "risk_on": [
      "Bond volatility (MOVE) -5% WoW \u2014 rates calming. \u2192 Supportive for risk assets."
    ],
    "curve": [
      "2-10 spread positive at +40 bps \u2014 normal upward slope. \u2192 Healthy baseline.",
      "Regime: Bear Steepener \u2014 long rates rising faster than short \u2014 growth/inflation/issuance. \u2192 Pressures long bonds & REITs/utilities."
    ],
    "trend": [
      "HY OAS: possible reversal \u2014 spreads turning WIDER (credit risk building) [early/low-conviction, 35/100]",
      "BBB OAS: possible reversal \u2014 spreads turning WIDER (credit risk building) [moderate, 40/100]",
      "2-10 Spread: possible reversal \u2014 curve steepening [early/low-conviction, 35/100]"
    ]
  }
}