{
  "spx_gamma": 12.3,
  "spx_spot": 7533.77,
  "spx_flip": 7521.49,
  "timestamp": "2026-07-16 22:54:47",
  "symbol": "_SPX",
  "gamma_throttle": 5.86,
  "rv_10day": 8.81,
  "vix": 16.73,
  "dist_to_flip_pct": 0.16,
  "regime": "WEAK POSITIVE GAMMA",
  "regime_description": "Mild positive gamma. Some suppression but fragile.",
  "risk_level": "MODERATE",
  "position_size": "50-75% of normal",
  "vol_signal": "CAUTION - REDUCE EXPOSURE",
  "dir_signal": "NO CLEAR DIRECTION",
  "key_levels": {
    "gamma_flip": 7521.0,
    "put_wall": 7296.0,
    "call_wall": 7760.0,
    "danger_zone": 7145.0
  }
}