{
  "ticker": "^IXIC",
  "forecast_date": "2026-06-30",
  "based_on_date": "2026-06-29",
  "based_on_close": 25820.14453125,
  "vix": 29.3700008392334,
  "regime": "chop",
  "forecast_high": 26325.66502512916,
  "forecast_low": 25133.924253288053,
  "high_pct": 1.9578530757925545,
  "low_pct": -2.6576934034254465,
  "range_width": 1191.7407718411087,
  "floor_active": true,
  "reference_levels": {
    "trr_50": 26108.136149246766,
    "llr_95": 25205.930811911494,
    "llr_90": 25299.655409735067,
    "llr_80": 25367.491421732106
  },
  "risks": [
    "Range persistence detected (1.38x median) \u2014 floor applied",
    "VXN at 29.4, approaching get_out threshold (30)",
    "Predicted range (4.62%) above 90th percentile for regime"
  ],
  "timestamp": "2026-06-29 19:34:26 EST",
  "model_version": "v5",
  "status": "success"
}