{
  "ticker": "^GSPC",
  "forecast_date": "2026-07-20",
  "based_on_date": "2026-07-17",
  "based_on_close": 7457.68994140625,
  "vix": 18.770000457763672,
  "regime": "investible",
  "forecast_high": 7509.630362485629,
  "forecast_low": 7336.339067878192,
  "high_pct": 0.6964679610907106,
  "low_pct": -1.6271911876397482,
  "range_width": 173.29129460743752,
  "floor_active": false,
  "reference_levels": {
    "trr_50": 7475.974392005289,
    "llr_90": 7353.197911754219,
    "llr_80": 7393.588000286896
  },
  "risks": [
    "High VIX velocity (19.8%) \u2014 elevated tail risk",
    "Predicted range (2.32%) above 90th percentile for regime"
  ],
  "timestamp": "2026-07-17 19:15:29 EST",
  "model_version": "v4",
  "status": "success"
}